miniconfig_argparse/__init__.py
miniconfig_argparse/configjson.py
miniconfig_argparse/parsertree.py
miniconfig_argparse/transform.py
miniconfig_argparse/verbosity_adjustment.py
miniconfig_argparse-0.0.2.dist-info/DESCRIPTION.rst
miniconfig_argparse-0.0.2.dist-info/entry_points.txt
miniconfig_argparse-0.0.2.dist-info/METADATA
miniconfig_argparse-0.0.2.dist-info/metadata.json
miniconfig_argparse-0.0.2.dist-info/RECORD
miniconfig_argparse-0.0.2.dist-info/top_level.txt
miniconfig_argparse-0.0.2.dist-info/WHEEL
