Metadata-Version: 2.0
Name: miniconfig-argparse
Version: 0.0.2
Summary: argparser factory for miniconfig
Home-page: https://github.com/podhmo/miniconfig-argparse
Author: podhmo
Author-email: UNKNOWN
License: mit
Keywords: miniconfig,argparse
Platform: UNKNOWN
Classifier: Programming Language :: Python
Classifier: Programming Language :: Python :: Implementation :: CPython
Requires-Dist: miniconfig
Requires-Dist: cached-property
Requires-Dist: handofcats
Provides-Extra: docs
Provides-Extra: testing
